{
  "tornado": {
    "eventType": 0,
    "hasGlobalCooldown": false,
    "hasLocalCooldown": false,
    "globalCooldown": 0,
    "localCooldown": 0,
    "mod": "Twitch Toolkit (Unofficial)"
  },
  "tornados": {
    "eventType": 0,
    "hasGlobalCooldown": false,
    "hasLocalCooldown": false,
    "globalCooldown": 0,
    "localCooldown": 0,
    "mod": "Twitch Toolkit (Unofficial)"
  },
  "clearweather": {
    "eventType": 0,
    "hasGlobalCooldown": false,
    "hasLocalCooldown": false,
    "globalCooldown": 0,
    "localCooldown": 0,
    "mod": "Twitch Toolkit (Unofficial)"
  },
  "rain": {
    "eventType": 0,
    "hasGlobalCooldown": false,
    "hasLocalCooldown": false,
    "globalCooldown": 0,
    "localCooldown": 0,
    "mod": "Twitch Toolkit (Unofficial)"
  },
  "vomitrain": {
    "eventType": 0,
    "hasGlobalCooldown": false,
    "hasLocalCooldown": false,
    "globalCooldown": 0,
    "localCooldown": 0,
    "mod": "Twitch Toolkit (Unofficial)"
  },
  "foggyrain": {
    "eventType": 0,
    "hasGlobalCooldown": false,
    "hasLocalCooldown": false,
    "globalCooldown": 0,
    "localCooldown": 0,
    "mod": "Twitch Toolkit (Unofficial)"
  },
  "rainythunderstorm": {
    "eventType": 0,
    "hasGlobalCooldown": false,
    "hasLocalCooldown": false,
    "globalCooldown": 0,
    "localCooldown": 0,
    "mod": "Twitch Toolkit (Unofficial)"
  },
  "drythunderstorm": {
    "eventType": 0,
    "hasGlobalCooldown": false,
    "hasLocalCooldown": false,
    "globalCooldown": 0,
    "localCooldown": 0,
    "mod": "Twitch Toolkit (Unofficial)"
  },
  "snowgentle": {
    "eventType": 0,
    "hasGlobalCooldown": false,
    "hasLocalCooldown": false,
    "globalCooldown": 0,
    "localCooldown": 0,
    "mod": "Twitch Toolkit (Unofficial)"
  },
  "snowhard": {
    "eventType": 0,
    "hasGlobalCooldown": false,
    "hasLocalCooldown": false,
    "globalCooldown": 0,
    "localCooldown": 0,
    "mod": "Twitch Toolkit (Unofficial)"
  },
  "fog": {
    "eventType": 0,
    "hasGlobalCooldown": false,
    "hasLocalCooldown": false,
    "globalCooldown": 0,
    "localCooldown": 0,
    "mod": "Twitch Toolkit (Unofficial)"
  },
  "heatwave": {
    "eventType": 0,
    "hasGlobalCooldown": false,
    "hasLocalCooldown": false,
    "globalCooldown": 0,
    "localCooldown": 0,
    "mod": "Twitch Toolkit (Unofficial)"
  },
  "flashstorm": {
    "eventType": 0,
    "hasGlobalCooldown": false,
    "hasLocalCooldown": false,
    "globalCooldown": 0,
    "localCooldown": 0,
    "mod": "Twitch Toolkit (Unofficial)"
  },
  "coldsnap": {
    "eventType": 0,
    "hasGlobalCooldown": false,
    "hasLocalCooldown": false,
    "globalCooldown": 0,
    "localCooldown": 0,
    "mod": "Twitch Toolkit (Unofficial)"
  },
  "solarflare": {
    "eventType": 0,
    "hasGlobalCooldown": false,
    "hasLocalCooldown": false,
    "globalCooldown": 0,
    "localCooldown": 0,
    "mod": "Twitch Toolkit (Unofficial)"
  },
  "shortcircuit": {
    "eventType": 0,
    "hasGlobalCooldown": false,
    "hasLocalCooldown": false,
    "globalCooldown": 0,
    "localCooldown": 0,
    "mod": "Twitch Toolkit (Unofficial)"
  },
  "toxicfallout": {
    "eventType": 0,
    "hasGlobalCooldown": false,
    "hasLocalCooldown": false,
    "globalCooldown": 0,
    "localCooldown": 0,
    "mod": "Twitch Toolkit (Unofficial)"
  },
  "volcanicwinter": {
    "eventType": 0,
    "hasGlobalCooldown": false,
    "hasLocalCooldown": false,
    "globalCooldown": 0,
    "localCooldown": 0,
    "mod": "Twitch Toolkit (Unofficial)"
  },
  "eclipse": {
    "eventType": 0,
    "hasGlobalCooldown": false,
    "hasLocalCooldown": false,
    "globalCooldown": 0,
    "localCooldown": 0,
    "mod": "Twitch Toolkit (Unofficial)"
  },
  "aurora": {
    "eventType": 0,
    "hasGlobalCooldown": false,
    "hasLocalCooldown": false,
    "globalCooldown": 0,
    "localCooldown": 0,
    "mod": "Twitch Toolkit (Unofficial)"
  },
  "blight": {
    "eventType": 0,
    "hasGlobalCooldown": false,
    "hasLocalCooldown": false,
    "globalCooldown": 0,
    "localCooldown": 0,
    "mod": "Twitch Toolkit (Unofficial)"
  },
  "animaltame": {
    "eventType": 0,
    "hasGlobalCooldown": false,
    "hasLocalCooldown": false,
    "globalCooldown": 0,
    "localCooldown": 0,
    "mod": "Twitch Toolkit (Unofficial)"
  },
  "wandererjoins": {
    "eventType": 0,
    "hasGlobalCooldown": false,
    "hasLocalCooldown": false,
    "globalCooldown": 0,
    "localCooldown": 0,
    "mod": "Twitch Toolkit (Unofficial)"
  },
  "resourcepodcrash": {
    "eventType": 0,
    "hasGlobalCooldown": false,
    "hasLocalCooldown": false,
    "globalCooldown": 0,
    "localCooldown": 0,
    "mod": "Twitch Toolkit (Unofficial)"
  },
  "tradercaravan": {
    "eventType": 0,
    "hasGlobalCooldown": false,
    "hasLocalCooldown": false,
    "globalCooldown": 0,
    "localCooldown": 0,
    "mod": "Twitch Toolkit (Unofficial)"
  },
  "orbitaltraderarrival": {
    "eventType": 0,
    "hasGlobalCooldown": false,
    "hasLocalCooldown": false,
    "globalCooldown": 0,
    "localCooldown": 0,
    "mod": "Twitch Toolkit (Unofficial)"
  },
  "meteor": {
    "eventType": 0,
    "hasGlobalCooldown": false,
    "hasLocalCooldown": false,
    "globalCooldown": 0,
    "localCooldown": 0,
    "mod": "Twitch Toolkit (Unofficial)"
  },
  "maninblack": {
    "eventType": 0,
    "hasGlobalCooldown": false,
    "hasLocalCooldown": false,
    "globalCooldown": 0,
    "localCooldown": 0,
    "mod": "Twitch Toolkit (Unofficial)"
  },
  "madanimal": {
    "eventType": 0,
    "hasGlobalCooldown": false,
    "hasLocalCooldown": false,
    "globalCooldown": 0,
    "localCooldown": 0,
    "mod": "Twitch Toolkit (Unofficial)"
  },
  "psychicdrone": {
    "eventType": 0,
    "hasGlobalCooldown": false,
    "hasLocalCooldown": false,
    "globalCooldown": 0,
    "localCooldown": 0,
    "mod": "Twitch Toolkit (Unofficial)"
  },
  "psychicsoothe": {
    "eventType": 0,
    "hasGlobalCooldown": false,
    "hasLocalCooldown": false,
    "globalCooldown": 0,
    "localCooldown": 0,
    "mod": "Twitch Toolkit (Unofficial)"
  },
  "ambrosiasprout": {
    "eventType": 0,
    "hasGlobalCooldown": false,
    "hasLocalCooldown": false,
    "globalCooldown": 0,
    "localCooldown": 0,
    "mod": "Twitch Toolkit (Unofficial)"
  },
  "herdmigration": {
    "eventType": 0,
    "hasGlobalCooldown": false,
    "hasLocalCooldown": false,
    "globalCooldown": 0,
    "localCooldown": 0,
    "mod": "Twitch Toolkit (Unofficial)"
  },
  "farmanimals": {
    "eventType": 0,
    "hasGlobalCooldown": false,
    "hasLocalCooldown": false,
    "globalCooldown": 0,
    "localCooldown": 0,
    "mod": "Twitch Toolkit (Unofficial)"
  },
  "wildman": {
    "eventType": 0,
    "hasGlobalCooldown": false,
    "hasLocalCooldown": false,
    "globalCooldown": 0,
    "localCooldown": 0,
    "mod": "Twitch Toolkit (Unofficial)"
  },
  "rarethrumbos": {
    "eventType": 0,
    "hasGlobalCooldown": false,
    "hasLocalCooldown": false,
    "globalCooldown": 0,
    "localCooldown": 0,
    "mod": "Twitch Toolkit (Unofficial)"
  },
  "shipchunkdrop": {
    "eventType": 0,
    "hasGlobalCooldown": false,
    "hasLocalCooldown": false,
    "globalCooldown": 0,
    "localCooldown": 0,
    "mod": "Twitch Toolkit (Unofficial)"
  },
  "travelergroup": {
    "eventType": 0,
    "hasGlobalCooldown": false,
    "hasLocalCooldown": false,
    "globalCooldown": 0,
    "localCooldown": 0,
    "mod": "Twitch Toolkit (Unofficial)"
  },
  "visitorgroup": {
    "eventType": 0,
    "hasGlobalCooldown": false,
    "hasLocalCooldown": false,
    "globalCooldown": 0,
    "localCooldown": 0,
    "mod": "Twitch Toolkit (Unofficial)"
  },
  "skillincrease": {
    "eventType": 0,
    "hasGlobalCooldown": false,
    "hasLocalCooldown": false,
    "globalCooldown": 0,
    "localCooldown": 0,
    "mod": "Twitch Toolkit (Unofficial)"
  },
  "party": {
    "eventType": 0,
    "hasGlobalCooldown": false,
    "hasLocalCooldown": false,
    "globalCooldown": 0,
    "localCooldown": 0,
    "mod": "Twitch Toolkit (Unofficial)"
  },
  "alphabeavers": {
    "eventType": 0,
    "hasGlobalCooldown": false,
    "hasLocalCooldown": false,
    "globalCooldown": 0,
    "localCooldown": 0,
    "mod": "Twitch Toolkit (Unofficial)"
  },
  "shippartpoison": {
    "eventType": 0,
    "hasGlobalCooldown": false,
    "hasLocalCooldown": false,
    "globalCooldown": 0,
    "localCooldown": 0,
    "mod": "Twitch Toolkit (Unofficial)"
  },
  "shippartpsychic": {
    "eventType": 0,
    "hasGlobalCooldown": false,
    "hasLocalCooldown": false,
    "globalCooldown": 0,
    "localCooldown": 0,
    "mod": "Twitch Toolkit (Unofficial)"
  },
  "militaryaid": {
    "eventType": 0,
    "hasGlobalCooldown": false,
    "hasLocalCooldown": false,
    "globalCooldown": 0,
    "localCooldown": 0,
    "mod": "Twitch Toolkit (Unofficial)"
  },
  "raid": {
    "eventType": 0,
    "hasGlobalCooldown": false,
    "hasLocalCooldown": false,
    "globalCooldown": 0,
    "localCooldown": 0,
    "mod": "Twitch Toolkit (Unofficial)"
  },
  "dropraid": {
    "eventType": 0,
    "hasGlobalCooldown": false,
    "hasLocalCooldown": false,
    "globalCooldown": 0,
    "localCooldown": 0,
    "mod": "Twitch Toolkit (Unofficial)"
  },
  "sapperraid": {
    "eventType": 0,
    "hasGlobalCooldown": false,
    "hasLocalCooldown": false,
    "globalCooldown": 0,
    "localCooldown": 0,
    "mod": "Twitch Toolkit (Unofficial)"
  },
  "siegeraid": {
    "eventType": 0,
    "hasGlobalCooldown": false,
    "hasLocalCooldown": false,
    "globalCooldown": 0,
    "localCooldown": 0,
    "mod": "Twitch Toolkit (Unofficial)"
  },
  "mechanoidraid": {
    "eventType": 0,
    "hasGlobalCooldown": false,
    "hasLocalCooldown": false,
    "globalCooldown": 0,
    "localCooldown": 0,
    "mod": "Twitch Toolkit (Unofficial)"
  },
  "infestation": {
    "eventType": 0,
    "hasGlobalCooldown": false,
    "hasLocalCooldown": false,
    "globalCooldown": 0,
    "localCooldown": 0,
    "mod": "Twitch Toolkit (Unofficial)"
  },
  "manhunterpack": {
    "eventType": 0,
    "hasGlobalCooldown": false,
    "hasLocalCooldown": false,
    "globalCooldown": 0,
    "localCooldown": 0,
    "mod": "Twitch Toolkit (Unofficial)"
  },
  "predators": {
    "eventType": 0,
    "hasGlobalCooldown": false,
    "hasLocalCooldown": false,
    "globalCooldown": 0,
    "localCooldown": 0,
    "mod": "Twitch Toolkit (Unofficial)"
  },
  "randomdisease": {
    "eventType": 0,
    "hasGlobalCooldown": false,
    "hasLocalCooldown": false,
    "globalCooldown": 0,
    "localCooldown": 0,
    "mod": "Twitch Toolkit (Unofficial)"
  },
  "disease": {
    "eventType": 0,
    "hasGlobalCooldown": false,
    "hasLocalCooldown": false,
    "globalCooldown": 0,
    "localCooldown": 0,
    "mod": "Twitch Toolkit (Unofficial)"
  },
  "reviveanypawn": {
    "eventType": 0,
    "hasGlobalCooldown": false,
    "hasLocalCooldown": false,
    "globalCooldown": 0,
    "localCooldown": 0,
    "mod": "Twitch Toolkit (Unofficial)"
  },
  "pawn": {
    "eventType": 0,
    "hasGlobalCooldown": false,
    "hasLocalCooldown": false,
    "globalCooldown": 0,
    "localCooldown": 0,
    "mod": "Twitch Toolkit (Unofficial)"
  },
  "levelskill": {
    "eventType": 0,
    "hasGlobalCooldown": false,
    "hasLocalCooldown": false,
    "globalCooldown": 0,
    "localCooldown": 0,
    "mod": "Twitch Toolkit (Unofficial)"
  },
  "trait": {
    "eventType": 0,
    "hasGlobalCooldown": false,
    "hasLocalCooldown": false,
    "globalCooldown": 0,
    "localCooldown": 0,
    "mod": "Twitch Toolkit (Unofficial)"
  },
  "removetrait": {
    "eventType": 0,
    "hasGlobalCooldown": false,
    "hasLocalCooldown": false,
    "globalCooldown": 0,
    "localCooldown": 0,
    "mod": "Twitch Toolkit (Unofficial)"
  },
  "genderswap": {
    "eventType": 0,
    "hasGlobalCooldown": false,
    "hasLocalCooldown": false,
    "globalCooldown": 0,
    "localCooldown": 0,
    "mod": "Twitch Toolkit (Unofficial)"
  },
  "item": {
    "eventType": 0,
    "hasGlobalCooldown": false,
    "hasLocalCooldown": false,
    "globalCooldown": 0,
    "localCooldown": 0,
    "mod": "Twitch Toolkit (Unofficial)"
  },
  "prisoner": {
    "eventType": 0,
    "hasGlobalCooldown": false,
    "hasLocalCooldown": false,
    "globalCooldown": 0,
    "localCooldown": 0,
    "mod": "Twitch Toolkit (Unofficial)"
  },
  "visitcolony": {
    "eventType": 0,
    "hasGlobalCooldown": false,
    "hasLocalCooldown": false,
    "globalCooldown": 0,
    "localCooldown": 0,
    "mod": "Twitch Toolkit (Unofficial)"
  },
  "randominspire": {
    "eventType": 0,
    "hasGlobalCooldown": false,
    "hasLocalCooldown": false,
    "globalCooldown": 0,
    "localCooldown": 0,
    "mod": "Twitch Toolkit (Unofficial)"
  },
  "torytalkervote": {
    "eventType": 0,
    "hasGlobalCooldown": false,
    "hasLocalCooldown": false,
    "globalCooldown": 0,
    "localCooldown": 0,
    "mod": "Twitch Toolkit (Unofficial)"
  },
  "hodlbotvote": {
    "eventType": 0,
    "hasGlobalCooldown": false,
    "hasLocalCooldown": false,
    "globalCooldown": 0,
    "localCooldown": 0,
    "mod": "Twitch Toolkit (Unofficial)"
  },
  "reviveall": {
    "eventType": 0,
    "hasGlobalCooldown": false,
    "hasLocalCooldown": false,
    "globalCooldown": 0,
    "localCooldown": 0,
    "mod": "ToolkitUtils"
  },
  "reviveme": {
    "eventType": 0,
    "hasGlobalCooldown": false,
    "hasLocalCooldown": false,
    "globalCooldown": 0,
    "localCooldown": 0,
    "mod": "ToolkitUtils"
  },
  "healall": {
    "eventType": 0,
    "hasGlobalCooldown": false,
    "hasLocalCooldown": false,
    "globalCooldown": 0,
    "localCooldown": 0,
    "mod": "ToolkitUtils"
  },
  "healanypawn": {
    "eventType": 0,
    "hasGlobalCooldown": false,
    "hasLocalCooldown": false,
    "globalCooldown": 0,
    "localCooldown": 0,
    "mod": "ToolkitUtils"
  },
  "healme": {
    "eventType": 0,
    "hasGlobalCooldown": false,
    "hasLocalCooldown": false,
    "globalCooldown": 0,
    "localCooldown": 0,
    "mod": "ToolkitUtils"
  },
  "surgery": {
    "eventType": 0,
    "hasGlobalCooldown": false,
    "hasLocalCooldown": false,
    "globalCooldown": 0,
    "localCooldown": 0,
    "mod": "ToolkitUtils"
  },
  "passionshuffle": {
    "eventType": 0,
    "hasGlobalCooldown": false,
    "hasLocalCooldown": false,
    "globalCooldown": 0,
    "localCooldown": 0,
    "mod": "ToolkitUtils"
  },
  "replacetrait": {
    "eventType": 0,
    "hasGlobalCooldown": false,
    "hasLocalCooldown": false,
    "globalCooldown": 0,
    "localCooldown": 0,
    "mod": "ToolkitUtils"
  },
  "rescueme": {
    "eventType": 0,
    "hasGlobalCooldown": false,
    "hasLocalCooldown": false,
    "globalCooldown": 0,
    "localCooldown": 0,
    "mod": "ToolkitUtils"
  },
  "fullheal": {
    "eventType": 0,
    "hasGlobalCooldown": false,
    "hasLocalCooldown": false,
    "globalCooldown": 0,
    "localCooldown": 0,
    "mod": "ToolkitUtils"
  },
  "passion": {
    "eventType": 0,
    "hasGlobalCooldown": false,
    "hasLocalCooldown": false,
    "globalCooldown": 0,
    "localCooldown": 0,
    "mod": "ToolkitUtils"
  },
  "removepassion": {
    "eventType": 0,
    "hasGlobalCooldown": false,
    "hasLocalCooldown": false,
    "globalCooldown": 0,
    "localCooldown": 0,
    "mod": "ToolkitUtils"
  },
  "backpack": {
    "eventType": 0,
    "hasGlobalCooldown": false,
    "hasLocalCooldown": false,
    "globalCooldown": 0,
    "localCooldown": 0,
    "mod": "ToolkitUtils"
  },
  "settraits": {
    "eventType": 0,
    "hasGlobalCooldown": false,
    "hasLocalCooldown": false,
    "globalCooldown": 0,
    "localCooldown": 0,
    "mod": "ToolkitUtils"
  },
  "cleartraits": {
    "eventType": 0,
    "hasGlobalCooldown": false,
    "hasLocalCooldown": false,
    "globalCooldown": 0,
    "localCooldown": 0,
    "mod": "ToolkitUtils"
  },
  "use": {
    "eventType": 0,
    "hasGlobalCooldown": false,
    "hasLocalCooldown": false,
    "globalCooldown": 0,
    "localCooldown": 0,
    "mod": "ToolkitUtils"
  },
  "wear": {
    "eventType": 0,
    "hasGlobalCooldown": false,
    "hasLocalCooldown": false,
    "globalCooldown": 0,
    "localCooldown": 0,
    "mod": "ToolkitUtils"
  },
  "equip": {
    "eventType": 0,
    "hasGlobalCooldown": false,
    "hasLocalCooldown": false,
    "globalCooldown": 0,
    "localCooldown": 0,
    "mod": "ToolkitUtils"
  },
  "randomchildhood": {
    "eventType": 0,
    "hasGlobalCooldown": false,
    "hasLocalCooldown": false,
    "globalCooldown": 0,
    "localCooldown": 0,
    "mod": "ToolkitUtils"
  },
  "randomadulthood": {
    "eventType": 0,
    "hasGlobalCooldown": false,
    "hasLocalCooldown": false,
    "globalCooldown": 0,
    "localCooldown": 0,
    "mod": "ToolkitUtils"
  },
  "smite": {
    "eventType": 0,
    "hasGlobalCooldown": false,
    "hasLocalCooldown": false,
    "globalCooldown": 0,
    "localCooldown": 0,
    "mod": "ToolkitUtils"
  },
  "sanctuary": {
    "eventType": 0,
    "hasGlobalCooldown": false,
    "hasLocalCooldown": false,
    "globalCooldown": 0,
    "localCooldown": 0,
    "mod": "ToolkitUtils"
  }
}